[
  {
    "title": "Peugeot 508 SW BlueHDi 120 Allure",
    "item_url": "item-carro.html",
    "image_url": "assets/img/carrinha/20250517_105109.jpg",
    "price_old": "€ 12,800.00",
    "price": "🔥€ 11,600.00",
    "status": "disponível agora",
    "description": "&lt;div class=&quot;item-description&quot;&gt;\n&lt;div class=&quot;availability-container&quot;&gt;\n&lt;div class=&quot;availability-info&quot;&gt;\n&lt;span class=&quot;availability&quot;&gt;Disponível para retirada imediata&lt;/span&gt;\n&lt;/div&gt;\n\n&lt;/div&gt;\n&lt;h3&gt;Descrição&lt;/h3&gt;\n&lt;div class=&quot;highlight&quot;&gt;TOPO DE GAMA&lt;/div&gt;\n&lt;p&gt;Carrinha impecável, versão topo de gama com praticamente todos os extras de fábrica.&lt;br/&gt;\n                    Viatura familiar, conduzida maioritariamente em auto-estrada, sempre assistida em concessionário\n                    oficial/stand de confiança (livro de revisões disponível).&lt;br/&gt;\n                    Conta atualmente com 188 000 km; motor\n                    económico e isento de problemas mecânicos ou eletrónicos.\n                &lt;/p&gt;&lt;br/&gt;\n&lt;p&gt;&lt;strong&gt;Equipamento em destaque&lt;/strong&gt;\n&lt;ul&gt;\n&lt;li&gt;Teto panorâmico em vidro com cortina elétrica&lt;/li&gt;\n&lt;li&gt;Estofos em couro &amp;amp; tecido (bancos dianteiros aquecidos e com regulação elétrica + memória)&lt;/li&gt;\n&lt;li&gt;Sistema de navegação GPS com ecrã tátil de 7&quot;&lt;/li&gt;\n&lt;li&gt;Head-Up Display a cores&lt;/li&gt;\n&lt;li&gt;Faróis Full-LED + luzes diurnas LED + máximos automáticos&lt;/li&gt;\n&lt;li&gt;Cruise control + limitador de velocidade&lt;/li&gt;\n&lt;li&gt;Sensores de estacionamento dianteiros e traseiros + câmara de marcha-atrás&lt;/li&gt;\n&lt;li&gt;Porta-bagagens elétrico com abertura “mãos-livres”&lt;/li&gt;\n&lt;li&gt;Sistema Keyless (entrada e arranque sem chave)&lt;/li&gt;\n&lt;li&gt;Ar condicionado automático bi-zona&lt;/li&gt;\n&lt;li&gt;Jantes liga leve de 18&quot;&lt;/li&gt;\n&lt;li&gt;Sistema áudio Hi-Fi (subwoofer)&lt;/li&gt;\n&lt;li&gt;Retrovisores rebatíveis eletricamente, sensor de chuva/luz, ISOFIX, 6 airbags, ESP, etc.&lt;/li&gt;\n&lt;/ul&gt;\n&lt;/p&gt;\n&lt;/div&gt;",
    "id": "c4ee1c2e-c02a-405a-9b64-d9bf2a9fdbbd",
    "images": [
      "assets/img/carrinha/20250517_105109.jpg",
      "assets/img/carrinha/20250517_100920.jpg",
      "assets/img/carrinha/20250517_100931.jpg",
      "assets/img/carrinha/20250517_101004.jpg",
      "assets/img/carrinha/20250517_101013.jpg",
      "assets/img/carrinha/20250517_101025.jpg",
      "assets/img/carrinha/20250517_101036.jpg",
      "assets/img/carrinha/20250517_101049.jpg",
      "assets/img/carrinha/20250517_105103.jpg",
      "assets/img/carrinha/20250517_105116.jpg",
      "assets/img/carrinha/20250517_105126.jpg",
      "assets/img/carrinha/20250517_105136.jpg"
    ]
  },
  {
    "title": "Radiador a Óleo 2500W",
    "item_url": "item-radiador_a_o_leo_2500w-pt.html",
    "image_url": "assets/img/radiador_a_oleo_2500w/20250503_161433.jpg",
    "price_old": "€ 30.00",
    "price": "🔥€ 18.00",
    "status": "disponível agora",
    "description": "&lt;div class=&quot;item-description&quot;&gt;\n&lt;div class=&quot;availability-container&quot;&gt;\n&lt;div class=&quot;availability-info&quot;&gt;\n&lt;span class=&quot;availability&quot;&gt;Disponível para retirada imediata&lt;/span&gt;&lt;br/&gt;✌️ 2 unidades disponíveis\n                    &lt;/div&gt;\n\n&lt;/div&gt;\n&lt;h3&gt;Descrição&lt;/h3&gt;\n&lt;p&gt;O aquecedor a óleo KUNFT Kor-1319 é uma excelente opção para aquecer espaços interiores com mais de\n                    20\n                    m2. Com onze barras de aquecimento, o Aquecedor a Óleo KUNFT Kor-1319 é capaz de fornecer calor\n                    suficiente para manter o ambiente confortável em dias frios. Este aquecedor é branco e tem 24 cm de\n                    largura, 59,5 cm de altura e 48 cm de profundidade. Ele é equipado com rodas articuladas para\n                    facilitar o transporte. No entanto, é importante lembrar que este produto é adequado apenas para\n                    espaços bem isolados ou para utilização ocasional.&lt;br/&gt;&lt;br/&gt;O Aquecedor a Óleo KUNFT Kor-1319 funciona\n                    com óleo e tem três níveis de potência, com uma conexão de energia de 2500 W. Seu sistema de\n                    segurança garante tranquilidade e segurança durante o uso. Além disso, as dimensões indicadas já\n                    contemplam o artigo com as rodas montadas, e ao adquirir este produto, você receberá um manual de\n                    instruções detalhado na caixa.&lt;br/&gt;&lt;br/&gt;Este aquecedor é recomendado para uso no chão em espaços\n                    interiores, onde você precisa de um aquecimento adicional para manter o ambiente confortável. O\n                    Aquecedor a Óleo KUNFT Kor-1319 é adequado para pessoas que procuram um produto fácil de\n                    transportar, seguro e eficiente para aquecer o ambiente de forma confortável e\n                    acolhedora.&lt;br/&gt;&lt;br/&gt;Não percas a oportunidade de garantir o conforto e a praticidade que o Aquecedor\n                    a Óleo KUNFT Kor-1319 pode oferecer ao teu ambiente.&lt;/p&gt;\n&lt;/div&gt;",
    "id": "54b69483-d84b-44c4-8409-c3a452247bac",
    "images": [
      "assets/img/radiador_a_oleo_2500w/20250503_161433.jpg",
      "assets/img/radiador_a_oleo_2500w/20250503_161427.jpg",
      "assets/img/radiador_a_oleo_2500w/c71303d01b4e76c899f2c76df8a4c898c93fe8e0.webp",
      "assets/img/radiador_a_oleo_2500w/20250503_161430.jpg",
      "assets/img/radiador_a_oleo_2500w/7b240b29f2ff139ba2ff5b004cb6d736f618f9b7.webp",
      "assets/img/radiador_a_oleo_2500w/bc1157525b72fabe4a1f62722746422dacb5f76a.webp",
      "assets/img/radiador_a_oleo_2500w/b3e4d5d81451a1731aac2c124cdf47d06e95e3b0.webp"
    ]
  },
  {
    "title": "Tineco Floor One S5",
    "item_url": "item-tineco-pt.html",
    "image_url": "assets/img/tineco/71kptbl45il_ac_sl1500_.jpg",
    "price_old": "€ 259.00",
    "price": "🔥€ 199.00",
    "status": "disponível agora",
    "description": "&lt;div class=&quot;item-description&quot;&gt;&lt;h3&gt;Descrição&lt;/h3&gt;&lt;p&gt;Dois em um: Limpa a sujidade húmida e seca e aborda a sujidade difícil e pegajosa em solos duros com facilidade. Com a tecnologia de sensores iLoop Smart, de propriedade da Tineco, ajustará automaticamente a sucção, o fluxo de água e a velocidade do rolo de escovagem para limpar qualquer tipo de sujidade.&lt;br/&gt;Desempenho de limpeza de borda: O exclusivo rolo de escova Flor ONE S5 foi projetado para deslizar firmemente contra os rodapés e limpar cantos de difícil acesso. O chão fica completamente seco e sem riscas em questão de minutos.&lt;br/&gt;Uma grande melhoria: O reservatório de água limpa é 30% maior do que o da última geração de FLOOR ONE, permitindo limpar áreas maiores ininterruptamente. O sistema de depósito duplo mantém a água limpa e a água suja separadas, para que possa sempre limpar com água fresca.&lt;br/&gt;Tecnologia de sensor inteligente Tineco iLoop: o nosso sensor inteligente patenteado Tineco iLoop deteta a sujidade e ajusta automaticamente a potência de sucção, a velocidade do rolo e os níveis de água adequadamente, melhorando a eficiência da limpeza e o tempo de funcionamento da bateria.&lt;br/&gt;Autolimpeza com o pressionar de um botão: o ciclo de autolimpeza da Flor ONE S5 limpa profundamente o rolo e os tubos da escova para manutenção sem mãos. Após a limpeza, a secagem centrífuga remove eficazmente a água do rolo.&lt;/p&gt;&lt;/div&gt;",
    "id": "992afd58-ecdb-43c0-bba7-e00acaee1159",
    "images": [
      "assets/img/tineco/71kptbl45il_ac_sl1500_.jpg",
      "assets/img/tineco/81x9sixos-l_ac_sl1500_.jpg",
      "assets/img/tineco/812vbq7avsl_ac_sl1500_.jpg",
      "assets/img/tineco/716erfm6rdl_ac_sl1500_.jpg",
      "assets/img/tineco/81oq6rnr3ml_ac_sl1500_.jpg",
      "assets/img/tineco/81uh1fshil_ac_sl1500_.jpg",
      "assets/img/tineco/71shxmozx2l_ac_sl1500_.jpg",
      "assets/img/tineco/61a5mlgmlul_ac_sl1500_.jpg"
    ]
  },
  {
    "title": "2 x Bancos altos, preto / velatura castanha, 63 cm",
    "item_url": "item-banco_alto-pt.html",
    "image_url": "assets/img/banco_alto/20250503_154538.jpg",
    "price_old": "€ 70.00",
    "price": "🔥€ 30.00",
    "status": "disponível agora",
    "description": "&lt;div class=&quot;item-description&quot;&gt;\n&lt;div class=&quot;availability&quot;&gt;Disponível para retirada imediata&lt;/div&gt;✌️ 2 unidades - não vendidas em\n                separado\n                &lt;h3&gt;Descrição&lt;/h3&gt;\n&lt;p&gt;SANDSBERG&lt;br/&gt;Banco alto, preto/velatura castanha, 63 cm&lt;br/&gt;Este banco alto combina uma expressão de\n                    madeira acolhedora com metal resistente num design estreito que fica muito bonito até mesmo em\n                    espaços pequenos. O encosto com 2 ripas oferece uma sensação de flexibilidade para maior conforto e\n                    descontração.\n                &lt;h4&gt;Detalhes do produto&lt;/h4&gt;Este banco alto com encosto tem um design estreito que se\n                integra na decoração sem ocupar muito espaço visual na divisão. Leve, mas robusto o suficiente para\n                suportar as atividades do dia a dia.&lt;br/&gt;O encosto com 2 ripas é moldado e dobrado para uma sensação\n                de flexibilidade quando se encosta.&lt;br/&gt;Para tornar um assento mais macio ou dar um toque pessoal à\n                divisão, complete com um coxim num estilo e cor à sua escolha.&lt;br/&gt;O repousa-pés permite uma posição\n                de máxima descontração e conforto.&lt;br/&gt;Combina na perfeição com a mesa alta\n                SANDSBERG.\n                &lt;h4&gt;Medidas&lt;/h4&gt;Altura: 91 cm&lt;br/&gt;Altura do assento: 63 cm&lt;br/&gt;Testado para: 110\n                kg&lt;br/&gt;Largura: 39 cm&lt;br/&gt;Profundidade do assento: 37 cm&lt;br/&gt;Profundidade: 46 cm&lt;br/&gt;Largura do\n                assento: 39 cm&lt;/p&gt;\n&lt;/div&gt;",
    "id": "efa38536-7d49-458d-8db2-509997a2c7d4",
    "images": [
      "assets/img/banco_alto/20250503_154538.jpg",
      "assets/img/banco_alto/sandsberg-banco-alto-preto-velatura-castanha__1045202_pe842464_s5.avif",
      "assets/img/banco_alto/sandsberg-banco-alto-preto-velatura-castanha__1028046_pe835188_s5.avif",
      "assets/img/banco_alto/20250503_154434.jpg",
      "assets/img/banco_alto/sandsberg-banco-alto-preto-velatura-castanha__1045201_pe842465_s5.avif",
      "assets/img/banco_alto/20250503_154523.jpg",
      "assets/img/banco_alto/20250503_154508.jpg",
      "assets/img/banco_alto/sandsberg-banco-alto-preto-velatura-castanha__1068122_pe852972_s5.avif",
      "assets/img/banco_alto/20250503_154532.jpg"
    ]
  },
  {
    "title": "Shnuggle Baby Bath - com suporte",
    "item_url": "item-shnuggle_baby_bath-pt.html",
    "image_url": "assets/img/shnuggle_baby_bath/20250503_161855.jpg",
    "price_old": "",
    "price": "€ 45.00",
    "status": "disponível agora",
    "description": "&lt;div class=&quot;item-description&quot;&gt;\n&lt;div class=&quot;availability&quot;&gt;Disponível para retirada imediata&lt;/div&gt;\n&lt;h3&gt;Descrição&lt;/h3&gt;\n&lt;p&gt;Desfrute de um momento de banho seguro e sem estresse!\n                &lt;h4&gt;Especificações principais&lt;/h4&gt;Indicado\n                desde: Recém-nascido até 12 meses+&lt;br/&gt;Material: Plástico atóxico e livre de BPA&lt;br/&gt;Por que os pais\n                adoram a Banheira Shnuggle&lt;br/&gt;⭐ &quot;Simplesmente adoro esta banheira! Meu bebê se sente tão seguro e\n                confortável nela.&quot; – Sophie M.&lt;br/&gt;⭐ &quot;Mudou completamente a hora do banho! Tão fácil de usar e mantém\n                meu bebê feliz.&quot; – James T.&lt;br/&gt;⭐ &quot;Tamanho perfeito, e agora meu bebê aproveita cada banho!&quot; – Emily\n                R.&lt;/p&gt;\n&lt;/div&gt;",
    "id": "7080edc0-5dbd-419a-b905-45c2e645a2ec",
    "images": [
      "assets/img/shnuggle_baby_bath/20250503_161855.jpg",
      "assets/img/shnuggle_baby_bath/20250503_161845.jpg",
      "assets/img/shnuggle_baby_bath/20250503_161833.jpg"
    ]
  },
  {
    "title": "Berço TRAMA Cama Cosleep Musa Branco/Tola",
    "item_url": "item-berc_o-pt.html",
    "image_url": "assets/img/berco/00105318147054____1__1200x1200.avif",
    "price_old": "",
    "price": "🔥€ 175.00",
    "status": "disponível 20/jun",
    "description": "&lt;div class=&quot;item-description&quot;&gt;\n&lt;div class=&quot;availability&quot;&gt;Disponível para retirada à partir de 20 de junho&lt;/div&gt;\n&lt;h3&gt;Descrição&lt;/h3&gt;\n&lt;p&gt;TRAMA&lt;br/&gt;Cama Cosleep Musa Branco/Tola&lt;br/&gt;Características&lt;br/&gt;Cama Musa da linha Outfit da marca\n                    Trama, com cantos e saliências arredondadas, estrado regulável em 3 alturas e lateral amovível com\n                    sistema oculto munido de dispositivo de dupla segurança, fácil de usar com apenas uma mão.&lt;br/&gt;Quando\n                    usado com o kit co-sleep (vendido separadamente), o estrado passa a ter 5 posições de\n                    altura.&lt;br/&gt;Detalhes e Cuidados:&lt;br/&gt;- Estrado regulável em 3 alturas em versão cama.&lt;br/&gt;- 5 posições\n                    de estrado em versão cama co-sleep com kit co-sleep opcional aplicado (vendido separadamente).&lt;br/&gt;-\n                    Lateral amovível com sistema oculto.&lt;br/&gt;- Tintas e vernizes não tóxicos.&lt;br/&gt;- Material: Madeira de\n                    pinho / Melamina.&lt;br/&gt;- Dimensões internas: 120x60cm.&lt;br/&gt;- Dimensões externas versão cama: 123 x 66,5\n                    x 89cm.&lt;br/&gt;- Dimensões externas versão casa co-sleep: 123 x 78,5 x 89cm.&lt;br/&gt;\n&lt;div class=&quot;highlight&quot;&gt;- Colchão\n                    incluído.&lt;/div&gt;\n&lt;/p&gt;\n&lt;/div&gt;",
    "id": "bd878539-43eb-4080-97ee-577401fcfc33",
    "images": [
      "assets/img/berco/00105318147054____1__1200x1200.avif",
      "assets/img/berco/20250503_160638.jpg",
      "assets/img/berco/20250503_160629.jpg",
      "assets/img/berco/20250503_160619.jpg"
    ]
  },
  {
    "title": "Poltrona, chapa de carvalho",
    "item_url": "#",
    "image_url": "assets/img/poltrona/poaeng-poltrona-chapa-de-betula-knisa-bege-claro__0571500_pe666933_s5.avif",
    "price_old": null,
    "price": null,
    "status": "VENDIDO",
    "id": "0835b54b-e82b-4d9b-af5a-c623479da8f7"
  },
  {
    "title": "3 x Cadeiras dobráveis",
    "item_url": "item-cadeira_dobra_vel_gunde-pt.html",
    "image_url": "assets/img/cadeira_dobravel_gunde/20250503_155939.jpg",
    "price_old": "",
    "price": "🔥€ 20.97 (3 un.)",
    "status": "disponível agora",
    "description": "&lt;div class=&quot;item-description&quot;&gt;\n&lt;div class=&quot;availability&quot;&gt;Disponível para retirada imediata&lt;/div&gt;😃 3 unidades - não vendidas em\n                separado\n                &lt;h3&gt;Descrição&lt;/h3&gt;\n&lt;p&gt;Cadeira dobrável&lt;br/&gt;Quanto valor cabe numa cadeira? Vale a pena olhar de novo. É dobrável e segura. É\n                    robusta, suporta até 100kg e é leve. Tem pouco espaço? Pode pendurá-la na parede.&lt;br/&gt;Detalhes do\n                    produto&lt;br/&gt;Pode fechar a cadeira para economizar espaço quando não está a usá-la.&lt;br/&gt;A cadeira vem\n                    pré-montada, para que a possa começar a usar desde logo.&lt;br/&gt;É fácil de transportar e pendurar na\n                    parede graças à pega recortada no encosto.&lt;br/&gt;Bloqueia quando aberta, para impedir que possa\n                    dobrar-se acidentalmente.\n                &lt;h4&gt;Medidas&lt;/h4&gt;Testado para: 100 kg&lt;br/&gt;Largura: 41 cm&lt;br/&gt;Profundidade: 45\n                cm&lt;br/&gt;Altura: 78 cm&lt;br/&gt;Largura do assento: 37 cm&lt;br/&gt;Profundidade do assento: 34 cm&lt;br/&gt;Altura do\n                assento: 45 cm&lt;/p&gt;\n&lt;/div&gt;",
    "id": "67ce29f8-2cbd-4711-8839-d4a96098f2ce",
    "images": [
      "assets/img/cadeira_dobravel_gunde/20250503_155939.jpg",
      "assets/img/cadeira_dobravel_gunde/20250503_160002.jpg",
      "assets/img/cadeira_dobravel_gunde/gunde-folding-chair-white__0872551_pe590566_s5.avif",
      "assets/img/cadeira_dobravel_gunde/20250503_155929.jpg",
      "assets/img/cadeira_dobravel_gunde/gunde-cadeira-dobravel-preto__0997019_pe822589_s5.avif",
      "assets/img/cadeira_dobravel_gunde/0728314_pe736185_s4.jpg"
    ]
  },
  {
    "title": "Cadeira de Escritório Executiva\n                        MITSAI Roma Preto",
    "item_url": "item-cadeira_de_escrito_rio_executiva_mitsai-pt.html",
    "image_url": "assets/img/cadeira_de_escritorio_executiva_mitsai/24ef2c80937c34e69da5cbef88954cd858b9e1f1.webp",
    "price_old": "€ 55.00",
    "price": "€ 50.00",
    "status": "disponível agora",
    "description": "&lt;div class=&quot;item-description&quot;&gt;\n&lt;div class=&quot;availability&quot;&gt;Disponível para retirada imediata&lt;/div&gt;\n&lt;h3&gt;Descrição&lt;/h3&gt;\n&lt;p&gt;\n                    Especificações Técnicas&lt;br/&gt;- Cadeira executiva ergonômica MITSAI Roma.&lt;br/&gt;- Altura ajustável por\n                    mecanismo de elevação a gás.&lt;br/&gt;- Assento com inclinação e função de travamento.&lt;br/&gt;- Apoios de\n                    braço acolchoados para maior conforto.&lt;br/&gt;- Base de nylon com cinco rodas para mobilidade.&lt;br/&gt;-\n                    Revestida em couro sintético preto.\n                &lt;/p&gt;\n&lt;/div&gt;",
    "id": "afd13f7a-1195-44d8-a480-6e5db37397ad",
    "images": [
      "assets/img/cadeira_de_escritorio_executiva_mitsai/24ef2c80937c34e69da5cbef88954cd858b9e1f1.webp",
      "assets/img/cadeira_de_escritorio_executiva_mitsai/875c66269d17106340b7f9c9ff59f43a5f44fdfa.webp",
      "assets/img/cadeira_de_escritorio_executiva_mitsai/21321649580ab304452fd6d708bd00906916b35a.webp",
      "assets/img/cadeira_de_escritorio_executiva_mitsai/e082badcce7334801a0594611af9c3b33c6894ba.jpeg"
    ]
  },
  {
    "title": "Cadeira escritório",
    "item_url": "item-cadeira_escrito_rio-pt.html",
    "image_url": "assets/img/cadeira_escritorio/762f9382-58d0-4e38-b27a-271847ecfee5.jpeg",
    "price_old": "€ 45.00",
    "price": "€ 40.00",
    "status": "disponível agora",
    "description": "&lt;div class=&quot;item-description&quot;&gt;\n&lt;div class=&quot;availability&quot;&gt;Disponível para retirada imediata&lt;/div&gt;\n&lt;h3&gt;Descrição&lt;/h3&gt;\n&lt;p&gt;Cadeira de escritório&lt;/p&gt;\n&lt;/div&gt;",
    "id": "2dd64836-8fd6-49f5-ad2d-7cd61c868a57",
    "images": [
      "assets/img/cadeira_escritorio/762f9382-58d0-4e38-b27a-271847ecfee5.jpeg",
      "assets/img/cadeira_escritorio/20250503_163617.jpg",
      "assets/img/cadeira_escritorio/20250503_163611.jpg"
    ]
  },
  {
    "title": "Cadeira de Refeição KINDERKRAFT Yummy Grey",
    "item_url": "item-cadeira_de_refeic_a_o-pt.html",
    "image_url": "assets/img/cadeira_de_refeicao/0b0e15ee25d2ce819355ab5abdd298d88512a711.webp",
    "price_old": "€ 59.00",
    "price": "€ 55.00",
    "status": "disponível agora",
    "description": "&lt;div class=&quot;item-description&quot;&gt;\n&lt;div class=&quot;availability&quot;&gt;Disponível para retirada à partir de 20 de junho&lt;/div&gt;\n&lt;h3&gt;Descrição&lt;/h3&gt;\n&lt;p&gt;• MULTIFUNCIONAL: YUMMY é uma cadeira de\n                    bebê adequada para crianças que conseguem sentar-se sozinhas (a partir dos 6 meses aprox.) até\n                    pesarem no máximo 15 kg (aprox. 3 anos). Graças à opção de dobrar para um tamanho compacto, é fácil\n                    de guardar , pode colocá-lo num canto ou num armário. Você também pode levá-lo nas\n                    férias.&lt;br/&gt;• AJUSTÁVEL: 7 níveis de altura, graças aos quais você pode ajustá-lo a diferentes mesas.\n                    O encosto pode ser ajustado em 3 faixas (é possível a posição semi-reclinável) e um apoio para os\n                    pés ajustável permite ajustar a cadeira alta à criança e adaptar um apoio para os pés\n                    ajustável &amp;gt;postura correta durante o aprendizado da alimentação. A bandeja dupla face possui 3\n                    níveis de regulagem (distância em relação ao bebê) e pode ser instalada nas pernas\n                    traseiras.&lt;br/&gt;• SEGURO: está equipado com cintos de segurança de 5 pontos ajustáveis com protetores\n                    que podem ser lavados livremente. Possui uma estrutura estável e cumpre a norma EN 14988:2017 para\n                    cadeiras altas para bebés.&lt;br/&gt;• PRÁTICO: a cadeira alta é fácil de dobrar, limpar e guardar na\n                    vertical . A capa de couro ecológico pode ser facilmente removida e limpa: basta passar um pano\n                    úmido. É anti-manchas. A moldura era feita de metal sólido. As pernas possuem rodas que não\n                    danificam o chão durante o transporte da cadeira alta.&lt;br/&gt;• COM ACESSÓRIOS: Possui também\n                    uma bandeja ajustável frente e verso que facilita a colocação da criança na cadeira alta.&lt;/p&gt;\n&lt;/div&gt;",
    "id": "0c8f482b-194c-4c0b-818e-06cbfbc96fe1",
    "images": [
      "assets/img/cadeira_de_refeicao/0b0e15ee25d2ce819355ab5abdd298d88512a711.webp",
      "assets/img/cadeira_de_refeicao/ac7842ed610c66cb542d90f71572aed60e86259f.webp",
      "assets/img/cadeira_de_refeicao/73a1417080af731062697060ae8cf443294cbc2f.webp",
      "assets/img/cadeira_de_refeicao/20250503_155906.jpg",
      "assets/img/cadeira_de_refeicao/20250503_155900.jpg",
      "assets/img/cadeira_de_refeicao/20250503_155853.jpg",
      "assets/img/cadeira_de_refeicao/20250503_155843.jpg",
      "assets/img/cadeira_de_refeicao/20250503_155855.jpg",
      "assets/img/cadeira_de_refeicao/ff5ad8678dec4ce356ea96114708b0c989eb99f6.webp",
      "assets/img/cadeira_de_refeicao/20250503_160050.jpg",
      "assets/img/cadeira_de_refeicao/20250503_160051.jpg"
    ]
  },
  {
    "title": "4 x Cadeiras de jantar",
    "item_url": "item-cadeiras_sala-pt.html",
    "image_url": "assets/img/cadeiras_sala/20250503_154601.jpg",
    "price_old": "€ 200.00",
    "price": "€ 180.00",
    "status": "disponível agora",
    "description": "&lt;div class=&quot;item-description&quot;&gt;\n&lt;div class=&quot;availability&quot;&gt;Disponível para retirada imediata&lt;/div&gt;\n&lt;h3&gt;Descrição&lt;/h3&gt;\n&lt;p&gt;FANBYN&lt;br/&gt;Cadeira de jantar&lt;br/&gt;Cadeira do ikea com menos de um ano de uso.&lt;br/&gt;Como nova.&lt;/p&gt;\n&lt;/div&gt;",
    "id": "92d12a54-de81-48d6-95ac-d6cade39c7b0",
    "images": [
      "assets/img/cadeiras_sala/20250503_154601.jpg",
      "assets/img/cadeiras_sala/20250503_154744.jpg",
      "assets/img/cadeiras_sala/20250503_154552.jpg",
      "assets/img/cadeiras_sala/20250503_154722.jpg"
    ]
  },
  {
    "title": "Cama casal completa com cabeceira e colchão, branco,\n160x200 cm",
    "item_url": "item-cama_casal_branca-pt.html",
    "image_url": "assets/img/cama_casal_branca/20250503_162306.jpg",
    "price_old": null,
    "price": null,
    "status": "VENDIDO",
    "description": "&lt;div class=&quot;item-description&quot;&gt;\n&lt;div class=&quot;availability&quot;&gt;Disponível para retirada à partir de 20 de junho&lt;/div&gt;\n&lt;h3&gt;Descrição&lt;/h3&gt;\n&lt;p&gt;BRIMNES&lt;br/&gt;Cabeceira c/arrumação, branco, 160 cm&lt;br/&gt;Se tem pouco espaço, experimente pôr tudo atrás\n                    das costas. A arrumação oculta para livros, revistas e todas as outras coisas que gosta de ter à mão\n                    faz da cabeceira BRIMNES uma heroína dos espaços pequenos.\n                &lt;h4&gt;Detalhes do produto&lt;/h4&gt;Não precisa de\n                uma mesa de cabeceira quando tem arrumação integrada na cabeceira de cama. Além de poupar espaço,\n                facilita o acesso às caixas ou às gavetas por baixo da cama. Além disso, é mais fácil de\n                aspirar.&lt;br/&gt;Uma das prateleiras pode ser ajustada em três posições diferentes.&lt;br/&gt;Passe os cabos dos\n                candeeiros e dos carregadores pelos orifícios da parte de cima da cabeceira de cama para não ficarem\n                à vista.\n                &lt;h4&gt;Medidas&lt;/h4&gt;Largura: 166 cm&lt;br/&gt;Profundidade: 28 cm&lt;br/&gt;Altura: 111 cm&lt;br/&gt;Largura do\n                colchão: 160 cm&lt;br/&gt;Escolha um tamanho diferente&lt;br/&gt;BRIMNES&lt;br/&gt;Estrutura cama c/arrumação,\n                branco, 160x200 cm&lt;br/&gt;Quando vive num espaço pequeno, tem de ser engenhoso. Talvez seja por isso que\n                está a ver esta estrutura de cama com quatro espaçosas gavetas. A gama BRIMNES tem vários heróis que\n                o ajudam a poupar espaço.&lt;h4&gt;Medidas&lt;/h4&gt;Comprimento: 206 cm&lt;br/&gt;Largura: 166 cm&lt;br/&gt;Altura: 47\n                cm&lt;br/&gt;Comprimento do colchão: 200 cm&lt;br/&gt;Largura do colchão: 160 cm&lt;br/&gt;Altura da gaveta\n                (interior): 20 cm&lt;br/&gt;Largura da gaveta (interior): 94 cm&lt;br/&gt;Profundidade de gaveta (interior): 54\n                cm&lt;br/&gt;Altura do pé da cama: 47 cm&lt;br/&gt;Altura da cabeceira: 111 cm&lt;h4&gt;Detalhes do produto&lt;/h4&gt;As quatro\n                gavetas grandes oferecem um espaço de arrumação amplo que fica oculto de forma elegante por baixo da\n                cama. Perfeitas para arrumar edredões, almofadas e roupa de cama.&lt;br/&gt;Esta estrutura de cama compacta\n                cabe facilmente em espaços apertados e sob tetos baixos, permitindo maximizar o espaço do\n                quarto.&lt;br/&gt;Esta estrutura de cama versátil vai ficar perfeita com os móveis de quarto e os têxteis à\n                sua escolha.&lt;br/&gt;As laterais da cama permitem regular a altura do estrado para colchões de diferentes\n                espessuras.&lt;br/&gt;VALEVÅG&lt;br/&gt;Colchão molas ensacadas, extra firme/azul claro, 160x200 cm&lt;br/&gt;Colchão\n                extra firme com 24cm de altura e molas ensacadas individualmente. Permite a distribuição uniforme do\n                peso corporal pelas zonas de conforto, proporcionando um apoio mais suave na anca e nos ombros. A\n                camada espessa de espuma acrescenta conforto.&lt;h4&gt;Detalhes do produto&lt;/h4&gt;A combinação de sonho de\n                conforto e apoio com zonas de conforto e molas ensacadas que o ajudam a dormir profundamente.&lt;br/&gt;5\n                zonas de conforto onde mais precisa para suportar as ancas e os ombros, criando um alinhamento\n                natural da coluna.&lt;br/&gt;As molas ensacadas reagem de forma independente sem transferirem movimento e\n                acompanham os movimentos do seu corpo para darem apoio à sua coluna e articulações.&lt;br/&gt;As molas\n                ensacadas em todo o colchão permitem a circulação do ar para melhor respirabilidade e não perdem o\n                conforto mesmo se forem colocados 2 colchões lado a lado.&lt;br/&gt;Uma camada espessa de espuma na parte\n                superior oferece suavidade.&lt;br/&gt;O tecido elástico acolchoado suave acompanha os movimentos do seu\n                corpo e tem uma camada de estofo adicional para um maior efeito acolchoado.&lt;br/&gt;Pode sentar-se ou\n                dormir junto às extremidades sem cair, já que o colchão tem um reforço nas extremidades.&lt;br/&gt;O\n                colchão completo tem uma garantia de 10 anos. Pode saber mais sobre as condições da garantia no\n                respetivo folheto.&lt;br/&gt;O colchão é embalado em rolo, pelo que é mais fácil levar para\n                casa.&lt;br/&gt;Acrescente uma almofada adequada à sua posição para dormir e um protetor de colchão para\n                manter o colchão limpo.&lt;h4&gt;Medidas&lt;/h4&gt;Comprimento: 200 cm&lt;br/&gt;Largura: 160 cm&lt;br/&gt;Espessura: 24\n                cm&lt;br/&gt;Escolha um tamanho diferente&lt;/p&gt;\n&lt;/div&gt;",
    "id": "955bb806-df0c-483d-8192-40c3fd63c8d6",
    "images": [
      "assets/img/cama_casal_branca/20250503_162306.jpg",
      "assets/img/cama_casal_branca/brimnes-cabeceira-c-arrumacao-branco__0738855_pe741607_s5.webp",
      "assets/img/cama_casal_branca/brimnes-estrutura-cama-c-arrumacao-branco__1151024_pe884762_s5.avif",
      "assets/img/cama_casal_branca/20250503_162420.jpg",
      "assets/img/cama_casal_branca/valevag-colchao-molas-ensacadas-extra-firme-azul-claro__1155997_pe886835_s5.avif",
      "assets/img/cama_casal_branca/valevag-colchao-molas-ensacadas-extra-firme-azul-claro__1370955_pe958921_s5.avif",
      "assets/img/cama_casal_branca/brimnes-cabeceira-c-arrumacao-branco__0781055_pe760484_s5.avif",
      "assets/img/cama_casal_branca/valevag-colchao-molas-ensacadas-extra-firme-azul-claro__1150857_pe884903_s5.avif",
      "assets/img/cama_casal_branca/brimnes-estrutura-cama-c-arrumacao-branco__0860776_pe659486_s5.avif",
      "assets/img/cama_casal_branca/20250503_162430.jpg",
      "assets/img/cama_casal_branca/brimnes-cabeceira-c-arrumacao-branco__0636301_pe697796_s5.avif",
      "assets/img/cama_casal_branca/valevag-colchao-molas-ensacadas-extra-firme-azul-claro__0905227_pe783082_s5.avif"
    ]
  },
  {
    "title": "Cama de casal com cabeceira e colchão 140x200 cm",
    "item_url": "item-cama_casal_-_slattum-pt.html",
    "image_url": "assets/img/cama_casal_-_slattum/20250503_162722.jpg",
    "price_old": null,
    "price": null,
    "status": "VENDIDO",
    "description": "&lt;div class=&quot;item-description&quot;&gt;\n&lt;div class=&quot;availability&quot;&gt;Disponível para retirada à partir de 20 de junho&lt;/div&gt;\n&lt;h3&gt;Descrição&lt;/h3&gt;\n&lt;p&gt;SLATTUM&lt;br/&gt;Estrutura de cama estofada, 140x200 cm&lt;br/&gt;A estrutura de cama SLATTUM tem um estofo suave\n                    e uma cabeceira acolchoada que completam as linhas simples e elegantes. Fácil de gostar e de levar\n                    para casa, uma vez que toda a estrutura vem numa única embalagem.\n                &lt;h4&gt;Detalhes do produto&lt;/h4&gt;É fácil\n                de levar para casa uma vez que toda a estrutura de cama, incluindo o estrado, estão\n                bem-acondicionados numa única embalagem plana.&lt;br/&gt;Fácil de montar graças a um processo de montagem\n                simplificado, que provavelmente é mais fácil do que possa pensar.&lt;br/&gt;A capa fixa é feita de tecido\n                Vissle em poliéster, tingido por fiação. É um material duradouro com uma tecelagem suave e um efeito\n                agradável de dois tons.&lt;br/&gt;O design simples e versátil coordena-se facilmente com outros móveis para\n                quarto e adapta-se perfeitamente a qualquer quarto moderno.&lt;br/&gt;Pode aspirar facilmente por baixo da\n                estrutura de cama para manter o espaço limpo e sem pó.&lt;br/&gt;A cama tem muito espaço em baixo para\n                caixas de arrumação, ideal para guardar edredões e mantas extra.\n                &lt;h4&gt;Medidas&lt;/h4&gt;Comprimento: 206\n                cm&lt;br/&gt;Largura: 144 cm&lt;br/&gt;Altura do pé da cama: 40 cm&lt;br/&gt;Altura da cabeceira: 85 cm&lt;br/&gt;Comprimento do\n                colchão: 200 cm&lt;br/&gt;Largura do colchão: 140 cm&lt;br/&gt;Escolha um tamanho diferente&lt;br/&gt;ÅGOTNES&lt;br/&gt;Colchão\n                de espuma, firme/azul claro, 140x200 cm&lt;br/&gt;Este colchão básico, de espuma firme, tem 10cm de altura.\n                É feito de espuma elástica combinada com uma camada de enchimento suave.&lt;br/&gt;Detalhes do\n                produto&lt;br/&gt;Um colchão com uma camada de espuma e uma capa suave e duradoura.&lt;br/&gt;Uma camada de estofo\n                na capa oferece um efeito acolchoado.&lt;br/&gt;O colchão completo tem uma garantia de 10 anos. Pode saber\n                mais sobre as condições da garantia no respetivo folheto.&lt;br/&gt;O colchão é embalado em rolo, pelo que\n                é mais fácil levar para casa.&lt;br/&gt;Acrescente uma almofada adequada à sua posição para dormir e um\n                protetor de colchão para manter o colchão limpo.&lt;h4&gt;Medidas&lt;/h4&gt;Comprimento: 200 cm&lt;br/&gt;Largura: 140\n                cm&lt;br/&gt;Espessura: 10 cm&lt;br/&gt;Escolha um tamanho diferente&lt;/p&gt;\n&lt;/div&gt;",
    "id": "e595400c-10d3-4719-9f3f-6f1486e8b48d",
    "images": [
      "assets/img/cama_casal_-_slattum/agotnes-colchao-de-espuma-firme-azul-claro__0986608_pe818097_s5.avif",
      "assets/img/cama_casal_-_slattum/slattum-estrutura-de-cama-estofada-vissle-cinz-esc__1259335_pe926650_s5.avif",
      "assets/img/cama_casal_-_slattum/agotnes-colchao-de-espuma-firme-azul-claro__0975992_pe812953_s5.avif",
      "assets/img/cama_casal_-_slattum/20250503_162754.jpg",
      "assets/img/cama_casal_-_slattum/20250503_162750.jpg",
      "assets/img/cama_casal_-_slattum/20250503_162722.jpg",
      "assets/img/cama_casal_-_slattum/20250503_162726.jpg",
      "assets/img/cama_casal_-_slattum/slattum-estrutura-de-cama-estofada-vissle-cinz-esc__0747515_pe744565_s5.avif",
      "assets/img/cama_casal_-_slattum/slattum-estrutura-de-cama-estofada-vissle-cinz-esc__1259364_pe926662_s5.avif"
    ]
  },
  {
    "title": "Cama de solteiro completa com colchão novo 90 x 190 cm",
    "item_url": "item-cama_solteiro-pt.html",
    "image_url": "assets/img/cama_solteiro/20250503_161008.jpg",
    "price_old": "€ 260.00",
    "price": "🔥€ 129.00",
    "status": "disponível agora",
    "description": "&lt;div class=&quot;item-description&quot;&gt;\n&lt;div class=&quot;availability&quot;&gt;Disponível para retirada imediata&lt;/div&gt;\n&lt;h3&gt;Descrição&lt;/h3&gt;\n&lt;p&gt;Cama de solteiro&lt;br/&gt;sem descrição&lt;br/&gt;VESTERÖY&lt;br/&gt;Colchão molas ensacadas, firme/azul claro, 90x190\n                    cm&lt;br/&gt;Colchão firme de 20cm de altura com molas ensacadas individualmente e uma camada de espuma que\n                    proporcionam conforto e apoio. A capa com espuma extra e com um tecido elástico suave confere ainda\n                    mais conforto.\n                &lt;h4&gt;Detalhes do produto&lt;/h4&gt;Molas ensacadas que reagem de forma independente sem\n                transferirem movimento.&lt;br/&gt;As molas ensacadas em todo o colchão permitem a circulação do ar para\n                melhor respirabilidade e não perdem o conforto mesmo se forem colocados 2 colchões lado a\n                lado.&lt;br/&gt;Uma camada de espuma na parte superior oferece conforto.&lt;br/&gt;Capa em tecido elástico\n                acolchoado suave com uma camada de estofo adicional.&lt;br/&gt;O colchão completo tem uma garantia de 10\n                anos. Pode saber mais sobre as condições da garantia no respetivo folheto.&lt;br/&gt;O colchão é embalado\n                em rolo, pelo que é mais fácil levar para casa.&lt;br/&gt;Acrescente uma almofada adequada à sua posição\n                para dormir e um protetor de colchão para manter o colchão limpo.\n                &lt;h4&gt;Medidas&lt;/h4&gt;Comprimento: 190\n                cm&lt;br/&gt;Largura: 90 cm&lt;br/&gt;Espessura: 20 cm&lt;br/&gt;Escolha um tamanho diferente&lt;/p&gt;\n&lt;/div&gt;",
    "id": "f66f4666-209e-4dcc-8a51-3884546aab1c",
    "images": [
      "assets/img/cama_solteiro/vesteroey-colchao-molas-ensacadas-firme-azul-claro__1155952_pe886827_s5.avif",
      "assets/img/cama_solteiro/vesteroey-colchao-molas-ensacadas-firme-azul-claro__1150853_pe884906_s5.avif",
      "assets/img/cama_solteiro/20250503_161008.jpg",
      "assets/img/cama_solteiro/20250503_161027.jpg",
      "assets/img/cama_solteiro/20250503_160950.jpg",
      "assets/img/cama_solteiro/20250503_160959.jpg",
      "assets/img/cama_solteiro/20250503_161013.jpg"
    ]
  },
  {
    "title": "Cómoda c/6 gavetas, branco, 138x84 cm",
    "item_url": "item-co_moda_6_gavetas_branco_138x84_cm-pt.html",
    "image_url": "assets/img/comoda_6_gavetas_branco_138x84_cm/20250503_161740.jpg",
    "price_old": "€ 220.00",
    "price": "🔥€ 170.00",
    "status": "disponível agora",
    "description": "&lt;div class=&quot;item-description&quot;&gt;\n&lt;div class=&quot;availability&quot;&gt;Disponível para retirada imediata&lt;/div&gt;\n&lt;h3&gt;Descrição&lt;/h3&gt;\n&lt;p&gt;HAUGA&lt;br/&gt;Cómoda c/6 gavetas, branco, 138x84 cm&lt;br/&gt;Para usar no quarto ou em toda a casa, por si só ou\n                    com outros móveis da gama HAUGA. Esta cómoda larga tem muito espaço de arrumação e a parte superior\n                    é ideal para pôr os seus melhores objetos.\n                &lt;h4&gt;Detalhes do produto&lt;/h4&gt;É claro que a sua casa deve ser\n                um lugar seguro para toda a família. Por isso, incluímos um dispositivo de fixação, para que possa\n                fixar a cómoda à parede.&lt;br/&gt;Pensado para usar por si só em toda a casa ou como uma combinação\n                perfeita com outros móveis da gama HAUGA, quer para coordenar o estilo, quer para criar soluções de\n                arrumação maiores.&lt;br/&gt;Graças ao seu aspeto distinto e ao seu design funcional, os móveis da gama\n                HAUGA funcionam bem sozinhos e ainda melhor juntos. As laterais planas e lisas permitem criar um\n                estilo uniforme quando as peças são colocadas lado a lado.&lt;br/&gt;Uma peça versátil que pode ser\n                utilizada nas diferentes divisões da casa.&lt;br/&gt;Maximize a arrumação e crie um estilo coordenado,\n                criando a sua própria combinação de arrumação HAUGA.&lt;br/&gt;A caraterística prateleira superior é um\n                elemento comum a toda a gama HAUGA e reforça o estilo tradicional. Pode utilizá-la para colocar\n                chapéus, caixas ou objetos decorativos. Como tem um rebordo, fica sempre tudo no devido\n                lugar.&lt;br/&gt;Uma cómoda larga, com muita arrumação e espaço no topo para um candeeiro ou qualquer outro\n                artigo que queira destacar.&lt;br/&gt;Se quiser organizar o interior, pode complementar com acessórios de\n                interior da gama STUK.&lt;br/&gt;A estrutura é fácil de montar graças às cavilhas em cunha que encaixam\n                facilmente nos orifícios pré-furados.\n                &lt;h4&gt;Medidas&lt;/h4&gt;Largura: 138 cm&lt;br/&gt;Profundidade: 46\n                cm&lt;br/&gt;Altura: 84 cm&lt;br/&gt;Largura da gaveta (interior): 61 cm&lt;br/&gt;Profundidade de gaveta (interior): 38\n                cm&lt;br/&gt;Capacidade de arrumação: 221 l&lt;br/&gt;Gaveta com travão: 22.9 cm&lt;/p&gt;\n&lt;/div&gt;",
    "id": "56f247ac-277a-44bd-bb9a-9a23cb80fe6b",
    "images": [
      "assets/img/comoda_6_gavetas_branco_138x84_cm/20250503_161740.jpg",
      "assets/img/comoda_6_gavetas_branco_138x84_cm/20250503_161652.jpg",
      "assets/img/comoda_6_gavetas_branco_138x84_cm/hauga-comoda-c-6-gavetas-branco__0943808_pe797052_s5.avif",
      "assets/img/comoda_6_gavetas_branco_138x84_cm/hauga-comoda-c-6-gavetas-branco__0898785_pe782651_s5.avif",
      "assets/img/comoda_6_gavetas_branco_138x84_cm/20250503_161706.jpg",
      "assets/img/comoda_6_gavetas_branco_138x84_cm/20250503_161729.jpg",
      "assets/img/comoda_6_gavetas_branco_138x84_cm/20250503_161648.jpg",
      "assets/img/comoda_6_gavetas_branco_138x84_cm/20250503_161629.jpg"
    ]
  },
  {
    "title": "Mixer Bosh",
    "item_url": "item-varinha_ma_gica_bosh-pt.html",
    "image_url": "assets/img/placeholder.jpg",
    "price_old": "€ 50.00",
    "price": "🔥€ 39.00",
    "status": "disponível agora",
    "description": "&lt;div class=&quot;item-description&quot;&gt;\n&lt;div class=&quot;availability&quot;&gt;Disponível para retirada imediata&lt;/div&gt;\n&lt;h3&gt;Descrição&lt;/h3&gt;\n&lt;p&gt;Varinha Mágica + Acessórios BOSCH MSM66120 ErgoMixx (600 W - Prateado e Preto)&lt;br/&gt;Ação de corte\n                    eficaz para excelentes resultados de mistura e processamento.&lt;br/&gt;O pé QuattroBlade de excelente\n                    qualidade e lâminas afiadas proporciona uma ótima ação de corte para obter excelentes resultados de\n                    processamento em pouco tempo. É inclusive fácil processar ingredientes de grande dimensão. A função\n                    AntiSplash evita salpicos e ajuda a manter sua cozinha limpa.&lt;br/&gt;&lt;br/&gt;Ergonómica e leve ajusta-se\n                    perfeitamente a qualquer mão.&lt;br/&gt;Utilizar uma varinha nunca foi tão confortável. Ergonómica e leve,\n                    ajusta-se a qualquer mão. A sua pega soft touch, para além de ter botões grandes e fáceis de\n                    alcançar, garante uma sensação de máximo conforte com uma aderência perfeita e à prova de\n                    deslize.&lt;br/&gt;&lt;br/&gt;Consistência perfeita graças ao seletor de 12 velocidades e função turbo.&lt;br/&gt;Estará\n                    sempre no controlo das definições precisas para cada tarefa. Quer seja molho, sopa ou maionese,\n                    basta selecionar a velocidade mais adequada do seletor variável de 12 velocidades, dependendo dos\n                    resultados desejados. Para máxima potência e tarefas mais exigentes, basta pressionar o botão\n                    turbo.&lt;br/&gt;&lt;br/&gt;Copo de medição e mistura com tampa para medir, misturar e armazenar.&lt;br/&gt;O copo de\n                    mistura / medição é perfeito para medir ingredientes e misturar pequenas quantidades. Graças à\n                    tampa, pode manter os alimentos, o molho ou os ingredientes triturados no copo após a mistura e\n                    armazená-los no frigorífico.&lt;br/&gt;&lt;br/&gt;Anexe e retire o pé de varinha com um simples clique para fácil\nlimpeza.&lt;br/&gt;Uma limpeza fácil deve apenas levar alguns segundos. Depois de terminar de utilizar,\n                    solte o pé com um simples clique. Agora pode limpá-la de forma rápida e fácil em água corrente ou na\n                    máquina de lavar loiça.&lt;br/&gt;Características técnicas&lt;/p&gt;\n&lt;/div&gt;",
    "id": "7a3fbd7b-31ee-4739-934c-d9e91ff60f6a",
    "images": []
  },
  {
    "title": "Airfryer Philips",
    "item_url": "item-fritadeira_sem_o_leo_philips-pt.html",
    "image_url": "assets/img/fritadeira_sem_oleo_philips/hallbar-caixote-c-tampa-cinz-clr__0924796_pe788621_s5.webp",
    "price_old": "€ 98.22",
    "price": "🔥€ 65.00",
    "status": "disponível agora",
    "description": "&lt;div class=&quot;item-description&quot;&gt;\n&lt;div class=&quot;availability&quot;&gt;Disponível para retirada imediata&lt;/div&gt;\n&lt;h3&gt;Descrição&lt;/h3&gt;\n&lt;p&gt;Características técnicas&lt;/p&gt;\n&lt;/div&gt;",
    "id": "4ca1763a-75a5-41f0-bc84-26520f4cc943",
    "images": [
      "assets/img/fritadeira_sem_oleo_philips/hallbar-caixote-c-tampa-cinz-clr__0924796_pe788621_s5.webp",
      "assets/img/fritadeira_sem_oleo_philips/b302f96757fd0f5f7474333ad4bc4e5d6628c836.jpeg",
      "assets/img/fritadeira_sem_oleo_philips/20250503_160216.jpg",
      "assets/img/fritadeira_sem_oleo_philips/b33b88bf58ccbf867ca7eb5e49b2d53c7a9794ab.jpeg",
      "assets/img/fritadeira_sem_oleo_philips/20250503_160218.jpg"
    ]
  },
  {
    "title": "Espelho, ef carvalho 65x150 cm",
    "item_url": "#",
    "image_url": "assets/img/espelho_retangular/20250503_162339.jpg",
    "price_old": null,
    "price": null,
    "status": "VENDIDO",
    "id": "fa4f3f48-2752-4b67-9078-cdd49734e91d"
  },
  {
    "title": "Espelho redondo - chapa de nogueira, 60 cm",
    "item_url": "item-espelho_redondo_60_cm-pt.html",
    "image_url": "assets/img/espelho_redondo_60_cm/stockholm-espelho-chapa-de-nogueira__0320389_pe339482_s5.avif",
    "price_old": "€ 69.00",
    "price": "€ 59.00",
    "status": "disponível agora",
    "description": "&lt;div class=&quot;item-description&quot;&gt;\n&lt;div class=&quot;availability&quot;&gt;Disponível para retirada imediata&lt;/div&gt;\n&lt;h3&gt;Descrição&lt;/h3&gt;\n&lt;p&gt;STOCKHOLM&lt;br/&gt;Espelho, chapa de nogueira, 60 cm&lt;br/&gt;A forma elegante e a chapa de nogueira dão um\n                    caráter único a cada espelho. A moldura na base do espelho forma uma prateleira onde pode pousar o\n                    telemóvel ou a carteira.\n                &lt;h4&gt;Detalhes do produto&lt;/h4&gt;A moldura em redor da parte inferior do espelho\n                forma uma prateleira onde pode colocar maquilhagem, o telemóvel ou a carteira.&lt;br/&gt;Fornecido com\n                película de segurança, que minimiza os danos caso o espelho se parta.\n                &lt;h4&gt;Medidas&lt;/h4&gt;Profundidade: 10\n                cm&lt;br/&gt;Diâmetro: 60 cm&lt;br/&gt;Escolha um tamanho diferente&lt;/p&gt;\n&lt;/div&gt;",
    "id": "31a2db6d-708f-4615-820f-7b7061eeba51",
    "images": [
      "assets/img/espelho_redondo_60_cm/stockholm-espelho-chapa-de-nogueira__0320389_pe339482_s5.avif",
      "assets/img/espelho_redondo_60_cm/stockholm-espelho-chapa-de-nogueira__0752139_pe747322_s5.avif",
      "assets/img/espelho_redondo_60_cm/20250503_155307.jpg",
      "assets/img/espelho_redondo_60_cm/20250503_155312.jpg",
      "assets/img/espelho_redondo_60_cm/20250503_155315.jpg",
      "assets/img/espelho_redondo_60_cm/stockholm-espelho-chapa-de-nogueira__0633570_pe695904_s5.avif",
      "assets/img/espelho_redondo_60_cm/stockholm-espelho-chapa-de-nogueira__1091610_pe862535_s5.avif"
    ]
  },
  {
    "title": "Impressora Multifuncional Epson",
    "item_url": "item-impressora_epson-pt.html",
    "image_url": "assets/img/impressora_epson/20250503_163032.jpg",
    "price_old": "€ 80.00",
    "price": "🔥€ 49.00",
    "status": "disponível agora",
    "description": "&lt;div class=&quot;item-description&quot;&gt;\n&lt;div class=&quot;availability&quot;&gt;Disponível para retirada imediata&lt;/div&gt;\n&lt;h3&gt;Descrição&lt;/h3&gt;\n&lt;p&gt;Impressora Epson Multifuncional WorkForce WF-2850&lt;br/&gt;Especificações\n                    em:&lt;br/&gt;https://www.epson.pt/pt_PT/produtos/impressoras/inkjet/microempresa/workforce-wf-2850dwf/p/27268\n                &lt;/p&gt;\n&lt;/div&gt;",
    "id": "e6b1149a-23c6-4357-9156-6289a7a9ff7f",
    "images": [
      "assets/img/impressora_epson/20250503_163032.jpg",
      "assets/img/impressora_epson/27268_productpicture_lores_wf-2850dwf.webp",
      "assets/img/impressora_epson/20250503_163037.jpg",
      "assets/img/impressora_epson/20250503_163042.jpg",
      "assets/img/impressora_epson/20250503_163040.jpg"
    ]
  },
  {
    "title": "2 x Caixotes c/tampa, cinz clr, 22 l",
    "item_url": "item-lixo_ha_llbar_cozinha_-pt.html",
    "image_url": "assets/img/lixo_hallbar_cozinha/hallbar-caixote-c-tampa-cinz-clr__0924796_pe788621_s5.avif",
    "price_old": "€ 14.00 (un.)",
    "price": "€ 14.00 (un.)",
    "status": "disponível agora",
    "description": "&lt;div class=&quot;item-description&quot;&gt;\n&lt;div class=&quot;availability&quot;&gt;Disponível para retirada imediata&lt;/div&gt;\n&lt;h3&gt;Descrição&lt;/h3&gt;\n&lt;p&gt;Sabe como os seus resíduos podem transformar-se em novos recursos? A gama HÅLLBAR ajuda-o a separar\n                    os diferentes materiais em caixotes diferentes. Uma ação simples que é apenas o primeiro passo para\n                    dar uma nova vida ao desperdício.\n                &lt;h4&gt;Detalhes do produto&lt;/h4&gt;Os caixotes HÅLLBAR foram concebidos\n                para responderem a diferentes necessidades de separação de resíduos. Este caixote é perfeito para\n                separar cartão, plástico, papel, garrafas de vidro, latas, envelopes e folhetos publicitários.&lt;br/&gt;Os\n                caixotes HÅLLBAR são empilháveis, pelo que poupam espaço. Coloque caixotes do mesmo tamanho em cima\n                uns dos outros ou coloque os caixotes mais pequenos em cima dos maiores.&lt;br/&gt;É fácil aceder ao\n                caixote, mesmo quando está empilhado, graças à tampa incluída. Tem dobradiças e pode ser aberto de\n                duas formas.&lt;br/&gt;A tampa incluída oculta o conteúdo do caixote. Retira-se facilmente para facilitar a\n                limpeza ou caso prefira manter o caixote sempre aberto.&lt;br/&gt;Os caixotes podem ser usados de forma\n                independente, em qualquer local da sua casa, ou podem ser integrados num armário ou numa\n                gaveta.&lt;br/&gt;O autocolante incluído pode ser colado ao caixote para indicar o que está a separar.\n                Desenhe ou escreva no autocolante para que seja fácil identificar o que vai para o caixote.&lt;br/&gt;Ao\n                montar a estrutura extraível para separação de resíduos HÅLLBAR num armário, ou a estrutura para\n                caixotes de separação de resíduos HÅLLBAR numa gaveta alta MAXIMERA, os caixotes mantêm-se no lugar\n                e ficam com uma boa visibilidade e ao alcance.&lt;br/&gt;O caixote foi concebido com cantos arredondados, o\n                que facilita a limpeza.&lt;br/&gt;A pega dobrável permite levar facilmente o caixote até ao ecoponto.&lt;br/&gt;Um\n                aro no rebordo do caixote permite ocultar o saco, evitando que saia do sítio. Pode retirar-se para\n                facilitar a limpeza ou se não estiver a ser usado.\n                &lt;h4&gt;Medidas&lt;/h4&gt;Medida exterior inferior,\n                prof.: 32.1 cm&lt;br/&gt;Medida exterior inferior, larg.: 20.1 cm&lt;br/&gt;Medida exterior superior, prof.: 38.6\n                cm&lt;br/&gt;Medida exterior superior, larg.: 26.3 cm&lt;br/&gt;Altura: 32.6 cm&lt;br/&gt;Volume: 22 l&lt;br/&gt;Escolha um\n                tamanho diferente&lt;/p&gt;\n&lt;/div&gt;",
    "id": "84a61d3c-7d09-453b-a233-a72ccfcfbf58",
    "images": [
      "assets/img/lixo_hallbar_cozinha/hallbar-caixote-c-tampa-cinz-clr__0924796_pe788621_s5.avif",
      "assets/img/lixo_hallbar_cozinha/hallbar-caixote-c-tampa-cinz-clr__0742725_pe742784_s5.avif"
    ]
  },
  {
    "title": "Chicco Recipiente de fraldas",
    "item_url": "item-recipiente_de_fraldas_chicco-pt.html",
    "image_url": "assets/img/recipiente_de_fraldas_chicco/51ocjeo7opl_ac_sl1500_.jpg",
    "price_old": "€ 50.00",
    "price": "🔥€ 30.00",
    "status": "disponível agora",
    "description": "&lt;div class=&quot;item-description&quot;&gt;\n&lt;div class=&quot;availability&quot;&gt;Disponível para retirada imediata&lt;/div&gt;\n&lt;h3&gt;Descrição&lt;/h3&gt;\n&lt;p&gt;rollar.&lt;br/&gt;Cambiar los pañales y cambiar pañales es para todos los padres. Por eso Chicco ha\n                    desarrollado específicamente para la delicada piel de los bebés con forro transpirable para mantener\n                    la piel saludable cada día. Además, en Chicco Babycremes encontrarás ingredientes naturales y otros\n                    accesorios para pañales.&lt;br/&gt;Chicco Odour Off - Papelera para pañales&lt;br/&gt;El cubo de pañales Chicco\n                    funciona con bolsas de basura normales, por lo que no hay costes adicionales. Los olores\n                    desagradables no pueden escapar del cubo de pañales. Práctico y sencillo: Con una sola mano, el\n                    pañal se elimina en tres pasos rápidos. A pesar de su tamaño compacto y ahorra espacio, el cubo\n                    tiene capacidad para hasta 25 pañales. Se puede utilizar con bolsas de basura estándar.&lt;/p&gt;\n&lt;/div&gt;",
    "id": "ef078e35-616c-4dc2-aed3-d8bb659c7a7e",
    "images": [
      "assets/img/recipiente_de_fraldas_chicco/51ocjeo7opl_ac_sl1500_.jpg",
      "assets/img/recipiente_de_fraldas_chicco/20250503_155345.jpg",
      "assets/img/recipiente_de_fraldas_chicco/20250503_155351.jpg",
      "assets/img/recipiente_de_fraldas_chicco/61ziqjs34dl_ac_sl1500_.jpg",
      "assets/img/recipiente_de_fraldas_chicco/20250503_155356.jpg",
      "assets/img/recipiente_de_fraldas_chicco/20250503_155337.jpg",
      "assets/img/recipiente_de_fraldas_chicco/51yuuvbngol_ac_sl1500_.jpg",
      "assets/img/recipiente_de_fraldas_chicco/51nijxdm1il_ac_sl1500_.jpg"
    ]
  },
  {
    "title": "Caixote c/tampa de pressão, aço inoxidável, 4 l",
    "item_url": "item-lixeira_brogrund-pt.html",
    "image_url": "assets/img/lixeira_brogrund/brogrund-caixote-c-tampa-de-pressao-aco-inoxidavel__0733266_pe738908_s5.avif",
    "price_old": "€ 16.00",
    "price": "€ 15.00",
    "status": "disponível agora",
    "description": "&lt;div class=&quot;item-description&quot;&gt;\n&lt;div class=&quot;availability&quot;&gt;Disponível para retirada imediata&lt;/div&gt;\n&lt;h3&gt;Descrição&lt;/h3&gt;\n&lt;p&gt;Sóbria, simples e distinta. A gama BROGRUND oferece uma ampla variedade de acessórios práticos que\n                    transformam o caos em ordem na sua casa de banho e dão-lhe um estilo renovado e moderno.&lt;br/&gt;Detalhes\n                    do produto&lt;br/&gt;O caixote do lixo abre facilmente com uma ligeira pressão na parte superior da\n                    tampa.&lt;br/&gt;Fácil de manter limpo graças à superfície antidedadas.&lt;br/&gt;O design elegante faz com que o\n                    caixote caiba em espaços estreitos.&lt;br/&gt;Pode colocar o caixote no chão ou montá-lo na parede.&lt;br/&gt;O\n                    caixote é fácil de mover graças à pega na parte de trás.&lt;br/&gt;O saco do lixo pode ser facilmente\n                    fixado em volta das pegas do balde interior para ser menos visível do lado de fora.&lt;br/&gt;As pegas\n                    facilitam a remoção do balde interior.&lt;br/&gt;Pode usar este caixote em qualquer lugar da casa, mesmo\n                    nas áreas húmidas como a cozinha e a casa de banho.\n                &lt;h4&gt;Medidas&lt;/h4&gt;Largura: 21 cm&lt;br/&gt;Profundidade: 14\n                cm&lt;br/&gt;Altura: 27 cm&lt;br/&gt;Volume: 4 l&lt;/p&gt;\n&lt;/div&gt;",
    "id": "84ca74b7-7c7d-4657-951a-3c06771629b0",
    "images": [
      "assets/img/lixeira_brogrund/brogrund-caixote-c-tampa-de-pressao-aco-inoxidavel__0733266_pe738908_s5.avif",
      "assets/img/lixeira_brogrund/brogrund-caixote-c-tampa-de-pressao-aco-inoxidavel__0733264_pe738906_s5.avif",
      "assets/img/lixeira_brogrund/brogrund-caixote-c-tampa-de-pressao-aco-inoxidavel__0733265_pe738909_s5.avif",
      "assets/img/lixeira_brogrund/brogrund-caixote-c-tampa-de-pressao-aco-inoxidavel__0733267_pe738907_s5.avif"
    ]
  },
  {
    "title": "Secretária, branco, 142x50 cm",
    "item_url": "item-secretaria_branco_142x50-pt.html",
    "image_url": "assets/img/secretaria_branco_142x50/20250503_163547.jpg",
    "price_old": "€ 99.00",
    "price": "🔥€ 70.00",
    "status": "disponível agora",
    "description": "&lt;div class=&quot;item-description&quot;&gt;\n&lt;div class=&quot;availability&quot;&gt;Disponível para retirada imediata&lt;/div&gt;\n&lt;h3&gt;Descrição&lt;/h3&gt;\n&lt;p&gt;MICKE&lt;br/&gt;Secretária, branco, 142x50 cm&lt;br/&gt;Um estilo elegante e simples que se enquadra bem em\n                    qualquer lado. Combine com outras secretárias ou blocos de gavetas da gama MICKE para aumentar o seu\n                    espaço de trabalho. O design funcional da parte posterior permite ocultar os cabos\n                    inestéticos.\n                &lt;h4&gt;Detalhes do produto&lt;/h4&gt;Um tampo grande faz com que seja mais fácil ter espaço para\n                dois.&lt;br/&gt;A saída para cabos e compartimento na parte de trás mantém os cabos e as extensões ocultos\n                mas acessíveis.&lt;br/&gt;As pernas podem ser montadas à direita ou à esquerda, de acordo com as\n                necessidades.&lt;br/&gt;Pode ser usado para dividir um espaço, porque tem acabamento na parte de\n                trás.&lt;br/&gt;Gavetas com travão para se manterem no lugar.\n                &lt;h4&gt;Medidas&lt;/h4&gt;Peso máximo: 50\n                kg&lt;br/&gt;Largura: 142 cm&lt;br/&gt;Profundidade: 50 cm&lt;br/&gt;Altura: 75 cm&lt;/p&gt;\n&lt;/div&gt;",
    "id": "bcf6879e-3e58-48e8-82a7-95dfe4cf5332",
    "images": [
      "assets/img/secretaria_branco_142x50/20250503_163547.jpg",
      "assets/img/secretaria_branco_142x50/20250503_163538.jpg",
      "assets/img/secretaria_branco_142x50/20250503_163600.jpg",
      "assets/img/secretaria_branco_142x50/20250503_163559.jpg",
      "assets/img/secretaria_branco_142x50/micke-secretaria-branco__0736020_pe740347_s5.avif"
    ]
  },
  {
    "title": "Mesa, branco, 125x75 cm",
    "item_url": "item-mesa_sala-pt.html",
    "image_url": "assets/img/mesa_sala/20250503_154857.jpg",
    "price_old": "€ 50.00",
    "price": "€ 40.00",
    "status": "disponível agora",
    "description": "&lt;div class=&quot;item-description&quot;&gt;\n&lt;div class=&quot;availability&quot;&gt;Disponível para retirada imediata&lt;/div&gt;\n&lt;h3&gt;Descrição&lt;/h3&gt;\n&lt;p&gt;MELLTORP&lt;br/&gt;Mesa, branco, 125x75 cm&lt;br/&gt;Esta mesa adapta-se a todo o tipo de necessidades e gostos,\n                    desde o mais minimalista até às famílias que exigem robustez e durabilidade todos os dias. Coloque-a\n                    na cozinha ou no espaço de refeições. O design simples combina bem com muitos estilos.&lt;br/&gt;Detalhes\n                    do produto&lt;br/&gt;A mesa é muito robusta graças à estrutura de metal.&lt;br/&gt;Estrutura da mesa em metal\n                    resistente e tampo em melamina suave e duradouro.&lt;br/&gt;Esta mesa combina com as cadeiras LIDÅS,\n                    TEODORES, ÖSTANÖ e KÄTTIL para diferentes estilos.\n                &lt;h4&gt;Medidas&lt;/h4&gt;Comprimento: 125 cm&lt;br/&gt;Largura: 75\n                cm&lt;br/&gt;Altura: 74 cm&lt;br/&gt;Escolha um tamanho diferente&lt;/p&gt;\n&lt;/div&gt;",
    "id": "5d114855-6bec-45ae-ad64-d184a0fbaf88",
    "images": [
      "assets/img/mesa_sala/20250503_154857.jpg",
      "assets/img/mesa_sala/20250503_154842.jpg",
      "assets/img/mesa_sala/20250503_154836.jpg",
      "assets/img/mesa_sala/20250503_154751.jpg",
      "assets/img/mesa_sala/20250503_154828.jpg",
      "assets/img/mesa_sala/20250503_154859.jpg",
      "assets/img/mesa_sala/20250503_154848.jpg"
    ]
  },
  {
    "title": "Mesa, branco, 120x60 cm",
    "item_url": "item-mesa_120x60-pt.html",
    "image_url": "assets/img/mesa_120x60/20250525_105050.jpg",
    "price_old": "€ 30.00",
    "price": "€ 25.00",
    "status": "disponível agora",
    "description": "&lt;div class=&quot;item-description&quot;&gt;\n&lt;div class=&quot;availability&quot;&gt;Disponível para retirada imediata&lt;/div&gt;\n&lt;h3&gt;Descrição&lt;/h3&gt;\n&lt;p&gt;Mesa, 120x60 cm com pés&lt;br/&gt;Detalhes do Tampo&lt;br/&gt;O tampo de mesa tem orifícios pré-furados para que\n                    seja mais fácil fixar à estrutura inferior.&lt;br/&gt;A tecnologia &quot;board-on-frame&quot; permite obter um\n                    material resistente e leve com uma estrutura em madeira, aglomerado ou MDF e um enchimento em cartão\n                    reciclado. É fácil de transportar, requer menos matérias-primas e tem menos impacto\n                    ambiental.\n                &lt;h4&gt;Medidas&lt;/h4&gt;Comprimento: 120 cm&lt;br/&gt;Largura: 60 cm&lt;br/&gt;Espessura: 3.4 cm&lt;br/&gt;Detalhes dos\n                pés&lt;br/&gt;Os pés reguláveis tornam a mesa estável, mesmo em superfícies\n                irregulares.&lt;h4&gt;Medidas&lt;/h4&gt;Altura: 70 cm&lt;br/&gt;Diâmetro: 4 cm&lt;br/&gt;Peso máximo: 50 kg&lt;/p&gt;\n&lt;/div&gt;",
    "id": "30d5d9a3-3bd4-40f2-80b4-faa0ac69e15f",
    "images": [
      "assets\\img\\mesa_120x60\\20250525_105050.jpg",
      "assets\\img\\mesa_120x60\\20250525_104952.jpg",
      "assets\\img\\mesa_120x60\\20250525_105047.jpg",
      "assets/img/mesa_120x60/adils-perna-branco__0734621_pe739540_s5.avif",
      "assets/img/mesa_120x60/adils-perna-branco__1045176_pe842454_s5.avif",
      "assets/img/mesa_120x60/adils-perna-branco__0849380_pe559901_s5.avif",
      "assets/img/mesa_120x60/lagkapten-tampo-branco__0977795_pe813778_s5.avif"
    ]
  },
  {
    "title": "Secretária de trabalho com caveletes de altura ajustável 75\nx 150 cm",
    "item_url": "item-mesa_75_x_150_cm-pt.html",
    "image_url": "assets/img/mesa_75_x_150_cm/mittback-cavalete-betula__1105787_pe868475_s5.avif",
    "price_old": "€ 70.00",
    "price": "🔥€ 60.00",
    "status": "disponível agora",
    "description": "&lt;div class=&quot;item-description&quot;&gt;\n&lt;div class=&quot;availability&quot;&gt;Disponível para retirada imediata&lt;/div&gt;\n&lt;h3&gt;Descrição&lt;/h3&gt;\n&lt;p&gt;Mesa com cavaletes&lt;br/&gt;Tampo mesa\n                &lt;h4&gt;Medidas&lt;/h4&gt;75 x 150cm&lt;br/&gt;Cavalete, bétula, 58x70/93\n                cm&lt;h4&gt;Detalhes do produto&lt;/h4&gt;O cavalete MITTBACK tem uma função de inclinação que ajuda a criar o\n                conforto de que precisa para dar asas à sua criatividade quando trabalha em casa ou se dedica a um\n                passatempo.&lt;br/&gt;A madeira maciça é um material natural e duradouro.&lt;br/&gt;Pode optar por um tampo\n                direito ou inclinado, o que é bom para escrever, pintar ou desenhar, regulando o cavalete.&lt;br/&gt;Muito\n                espaço na prateleira por baixo do cavalete para colocar uma impressora, livros ou documentos. Ajuda\n                a manter o tampo arrumado e permite ter mais espaço de trabalho.&lt;h4&gt;Medidas&lt;/h4&gt;Largura: 58\n                cm&lt;br/&gt;Profundidade: 35 cm&lt;br/&gt;Altura mínima: 70 cm&lt;br/&gt;Altura máxima: 93 cm&lt;br/&gt;Peso: 4 kg&lt;/p&gt;\n&lt;/div&gt;",
    "id": "54a46f5a-35f6-47be-8cf5-285ec5bf7a9e",
    "images": [
      "assets/img/mesa_75_x_150_cm/mittback-cavalete-betula__1105787_pe868475_s5.avif",
      "assets/img/mesa_75_x_150_cm/mittback-cavalete-betula__1105743_pe868443_s5.webp",
      "assets/img/mesa_75_x_150_cm/20250503_154601.jpg",
      "assets/img/mesa_75_x_150_cm/mittback-cavalete-betula__1012807_ph176805_s5.avif"
    ]
  },
  {
    "title": "2 x Monitores ASUS VZ24EHE (23.8'' - FHD - IPS)",
    "item_url": "item-monitor_asus_vz24ehe_238-pt.html",
    "image_url": "assets/img/monitor_asus_vz24ehe_23.8/758312e4bc9f8ad92cb115f3eb5c3b12049c8a2e.webp",
    "price_old": "€ 139.00 (un.)",
    "price": "🔥€ 130.00 (un.)",
    "status": "disponível agora",
    "description": "&lt;div class=&quot;item-description&quot;&gt;\n&lt;div class=&quot;availability&quot;&gt;Disponível para retirada imediata&lt;/div&gt;\n&lt;h3&gt;Descrição&lt;/h3&gt;\n&lt;p&gt;Sobre o produto&lt;br/&gt;Monitor ASUS VZ24EHE (23.8&#x27;&#x27; - FHD - IPS)&lt;br/&gt;O Monitor ASUS VZ24EHE (23.8&#x27;&#x27; - FHD\n                    - IPS) é a escolha perfeita para quem busca qualidade e eficiência. Com tecnologia FreeSync, você\n                    terá uma experiência de jogo mais suave e sem cortes. Com uma taxa de atualização de 75 Hz e tempo\n                    de resposta de 1ms, esse monitor é ideal para jogos e para qualquer outra tarefa. Compatível com\n                    VESA de 75x75mm e conexões HDMI e VGA, este monitor oferece uma resolução FHD e um ângulo de visão\n                    de 178º, proporcionando imagens nítidas e claras em qualquer posição. Além disso, com 16,7 milhões\n                    de cores, você terá uma imagem rica em detalhes.&lt;br/&gt;&lt;br/&gt;O Monitor ASUS VZ24EHE é ecologicamente\n                    correto com uma classificação de energia E, economizando energia e reduzindo custos. Na caixa, você\n                    encontrará materiais impressos, cabo de alimentação e cabo VGA, proporcionando uma experiência de\n                    uso ainda mais completa e satisfatória.&lt;br/&gt;&lt;br/&gt;Com um design elegante na cor preta, o Monitor ASUS\n                    VZ24EHE (23.8&#x27;&#x27; - FHD - IPS) é perfeito para quem busca qualidade e praticidade em um único produto.\n                    Com uma altura que varia entre 31,7 e 39,2 cm e uma largura de 54 cm, esse monitor tem um formato\n                    plano e pesa apenas 4,2 kg, sendo fácil de transportar e de se adequar a qualquer\n                    ambiente.&lt;br/&gt;&lt;br/&gt;Este monitor é ideal para quem busca um produto de qualidade para jogos, trabalho\n                    ou entretenimento em geral. Com o Monitor ASUS VZ24EHE (23.8&#x27;&#x27; - FHD - IPS), você terá uma\n                    experiência incrível e poderá desfrutar de imagens nítidas e claras em qualquer\n                    posição.&lt;br/&gt;Características técnicas&lt;/p&gt;\n&lt;/div&gt;",
    "id": "3b26ac21-5ef0-4c1b-b8f2-3984de737752",
    "images": [
      "assets/img/monitor_asus_vz24ehe_23.8/758312e4bc9f8ad92cb115f3eb5c3b12049c8a2e.webp",
      "assets/img/monitor_asus_vz24ehe_23.8/cd80986241085b430dad5cabdfaff3652c27ce76.webp",
      "assets/img/monitor_asus_vz24ehe_23.8/8fd19e1d4882095cb87ab10012b928e10e52617f.webp"
    ]
  },
  {
    "title": "Jogo de panelas com 7 peças",
    "item_url": "item-set_7_pec_as_-_trem_de_cozinha_tefal-pt.html",
    "image_url": "assets/img/set_7_pecas_-_trem_de_cozinha_tefal/e01eb9caec2819f101d5c7f4450641298600adca.webp",
    "price_old": "🔥€ 149.00",
    "price": "🔥€ 129.00",
    "status": "disponível agora",
    "description": "&lt;div class=&quot;item-description&quot;&gt;\n&lt;div class=&quot;availability&quot;&gt;Disponível para retirada imediata&lt;/div&gt;\n&lt;h3&gt;Descrição&lt;/h3&gt;\n&lt;p&gt;Sobre o produto&lt;br/&gt;Set 7 Peças - Trem De Cozinha TEFAL Duetto + G719S734 (16/20/24cm)&lt;br/&gt;Com o set\n                    Duetto+ em aço inoxidável de alta qualidade, passe menos tempo na cozinha e mais tempo com aqueles\n                    que mais gosta!&lt;br/&gt;COADOR INCORPORADO&lt;br/&gt;Tampa com sistema de coador incorporado facilitando a\n                    coagem de líquidos após cozedura.&lt;br/&gt;MARCAS DE MEDIÇÃO NO INTERIOR&lt;br/&gt;Cozinhados precisos de acordo\n                    com as quantidades das suas receitas.&lt;br/&gt;THERMO-FUSION™ INTEGRAL&lt;br/&gt;Base de indução total e extra\n                    espessa, garante um aquecimento mais rápido e uma distribuição homogénea do calor para cozinhar de\n                    forma uniforme os alimentos.&lt;br/&gt;PEGAS COM REBITES&lt;br/&gt;As pegas ultrarresistentes com rebites,\n                    conferem maior segurança durante a utilização e durabilidade.&lt;br/&gt;COMPATÍVEL COM FORNO&lt;br/&gt;Bastante\n                    versátil o set Duetto+, da Tefal, é compatível com todas as fontes de calor e com o forno até 250ºC\n                    (exceto tampas).&lt;br/&gt;Características técnicas&lt;/p&gt;\n&lt;/div&gt;",
    "id": "9a336c44-d380-4ed8-a5dc-92997614a83f",
    "images": [
      "assets/img/set_7_pecas_-_trem_de_cozinha_tefal/e01eb9caec2819f101d5c7f4450641298600adca.webp",
      "assets/img/set_7_pecas_-_trem_de_cozinha_tefal/241176cd701e3be181b85f3133bea32bab9655c6.webp",
      "assets/img/set_7_pecas_-_trem_de_cozinha_tefal/cd5a0ab3d8015432a655c6e3c119b43fc643ca74.webp",
      "assets/img/set_7_pecas_-_trem_de_cozinha_tefal/9b805f010c6ecaf5d6befa0b93c9ce5001605dc7.webp",
      "assets/img/set_7_pecas_-_trem_de_cozinha_tefal/ad09acc301b2e55c9ba8f51b80a74a1f9803d580.webp",
      "assets/img/set_7_pecas_-_trem_de_cozinha_tefal/18f41e128af71d55a007b5196bbbdaaabf9895b1.webp"
    ]
  },
  {
    "title": "Estante de parede (prateleiras), branco,\n                        110x26 cm",
    "item_url": "item-estante_de_parede_branco_110x26_cm-pt.html",
    "image_url": "assets/img/estante_de_parede_branco_110x26_cm/lack-estante-de-parede-branco__0641087_pe700250_s5.avif",
    "price_old": "€ 15.00",
    "price": "€ 15.00",
    "status": "disponível agora",
    "description": "&lt;div class=&quot;item-description&quot;&gt;\n&lt;div class=&quot;availability&quot;&gt;Disponível para retirada imediata&lt;/div&gt;\n&lt;h3&gt;Descrição&lt;/h3&gt;\n&lt;p&gt;LACK&lt;br/&gt;Estante de parede, branco, 110x26 cm&lt;br/&gt;Esta estante de parede elegante faz o seu trabalho de\n                    forma discreta e quase invisível. Os suportes de suspensão ocultos permitem que se integre na\n                    parede, colocando os seus objetos preferidos em destaque.\n                &lt;h4&gt;Detalhes do produto&lt;/h4&gt;Com uma estante\n                de parede, pode aproveitar ao máximo a parede, libertando espaço no\n                chão.\n                &lt;h4&gt;Medidas&lt;/h4&gt;Comprimento: 110 cm&lt;br/&gt;Profundidade: 26 cm&lt;br/&gt;Espessura: 5 cm&lt;br/&gt;Peso máximo: 10\n                kg&lt;/p&gt;\n&lt;/div&gt;",
    "id": "d66edd0e-9410-4e69-b272-dc2e1448d8f3",
    "images": [
      "assets/img/estante_de_parede_branco_110x26_cm/lack-estante-de-parede-branco__0641087_pe700250_s5.avif",
      "assets/img/estante_de_parede_branco_110x26_cm/lack-estante-de-parede-branco__0670318_pe715443_s5.avif"
    ]
  },
  {
    "title": "Estante de parede (prateleiras), branco,\n                        190x26 cm",
    "item_url": "item-estante_de_parede_branco_190x26_cm-pt.html",
    "image_url": "assets/img/estante_de_parede_branco_190x26_cm/20250503_155224.jpg",
    "price_old": "€ 50.00",
    "price": "🔥€ 25.00",
    "status": "disponível agora",
    "description": "&lt;div class=&quot;item-description&quot;&gt;\n&lt;div class=&quot;availability&quot;&gt;Disponível para retirada imediata&lt;/div&gt;\n&lt;h3&gt;Descrição&lt;/h3&gt;\n&lt;p&gt;LACK&lt;br/&gt;Estante de parede, branco, 190x26 cm&lt;br/&gt;Esta estante de parede elegante faz o seu trabalho de\n                    forma discreta e quase invisível. Os suportes de suspensão ocultos permitem que se integre na\n                    parede, colocando os seus objetos preferidos em destaque.\n                &lt;h4&gt;Detalhes do produto&lt;/h4&gt;Com uma estante\n                de parede, pode aproveitar ao máximo a parede, libertando espaço no\n                chão.\n                &lt;h4&gt;Medidas&lt;/h4&gt;Comprimento: 190 cm&lt;br/&gt;Profundidade: 26 cm&lt;br/&gt;Espessura: 5 cm&lt;br/&gt;Peso máximo: 15\n                kg&lt;/p&gt;\n&lt;/div&gt;",
    "id": "58ab7592-4a9a-4221-9365-03b3c96735a0",
    "images": [
      "assets/img/estante_de_parede_branco_190x26_cm/20250503_155224.jpg",
      "assets/img/estante_de_parede_branco_190x26_cm/20250503_155227.jpg",
      "assets/img/estante_de_parede_branco_190x26_cm/20250503_155154.jpg",
      "assets/img/estante_de_parede_branco_190x26_cm/lack-estante-de-parede-branco__1206613_pe907552_s5.avif",
      "assets/img/estante_de_parede_branco_190x26_cm/lack-estante-de-parede-branco__0670320_pe715445_s5.avif",
      "assets/img/estante_de_parede_branco_190x26_cm/lack-estante-de-parede-branco__0246558_pe385543_s5.avif",
      "assets/img/estante_de_parede_branco_190x26_cm/20250503_155201.jpg"
    ]
  },
  {
    "title": "Móvel TV, branco, 180x40x38 cm",
    "item_url": "item-mo_vel_tv_branco_180x40x38_cm-pt.html",
    "image_url": "assets/img/movel_tv_branco_180x40x38_cm/besta-movel-tv-branco__0376997_pe516837_s5.avif",
    "price_old": null,
    "price": null,
    "status": "VENDIDO",
    "description": "&lt;div class=&quot;item-description&quot;&gt;\n&lt;div class=&quot;availability&quot;&gt;Disponível para retirada imediata&lt;/div&gt;\n&lt;h3&gt;Descrição&lt;/h3&gt;\n&lt;p&gt;BESTÅ&lt;br/&gt;Móvel TV, branco, 180x40x38 cm&lt;br/&gt;Não é só a televisão que é smart. Os móveis de TV BESTÅ\n                    combinam estilo contemporâneo com função prática. Terá muito espaço de arrumação e ajuda com os\n                    cabos que tendem a ficar desorganizados e com pó.\n                &lt;h4&gt;Detalhes do produto&lt;/h4&gt;Estruturas em diferentes\n                tamanhos; permitem a criação de uma solução adequada para a sua televisão.&lt;br/&gt;Pode optar por colocar\n                o móvel de TV no chão ou montado na parede para libertar espaço no chão.&lt;br/&gt;A saída de cabos na\n                parte de cima permite que os cabos entrem facilmente no móvel de TV.&lt;br/&gt;Os pés reguláveis permitem\n                que o móvel de TV se mantenha direito, mesmo num chão desnivelado.\n                &lt;h4&gt;Medidas&lt;/h4&gt;Largura: 180\n                cm&lt;br/&gt;Profundidade: 40 cm&lt;br/&gt;Altura: 38 cm&lt;br/&gt;Peso máximo da TV: 30 kg&lt;br/&gt;Escolha um tamanho\n                diferente&lt;/p&gt;\n&lt;/div&gt;",
    "id": "4ee8e888-c2b6-4fa7-809c-b26c96f98b11",
    "images": [
      "assets/img/movel_tv_branco_180x40x38_cm/besta-movel-tv-branco__0376997_pe516837_s5.avif",
      "assets/img/movel_tv_branco_180x40x38_cm/20250503_155124.jpg",
      "assets/img/movel_tv_branco_180x40x38_cm/besta-movel-tv-branco__0720087_pe732402_s5.avif",
      "assets/img/movel_tv_branco_180x40x38_cm/20250503_155059.jpg",
      "assets/img/movel_tv_branco_180x40x38_cm/20250503_155107.jpg",
      "assets/img/movel_tv_branco_180x40x38_cm/besta-movel-tv-branco__0843389_pe535717_s5.avif",
      "assets/img/movel_tv_branco_180x40x38_cm/besta-movel-tv-branco__1441964_pe986634_s5.avif"
    ]
  },
  {
    "title": "Sapateira",
    "item_url": "item-sapateira-pt.html",
    "image_url": "assets/img/sapateira/20250503_155657.jpg",
    "price_old": "€ 80.00",
    "price": "🔥€ 65.00",
    "status": "disponível agora",
    "description": "&lt;div class=&quot;item-description&quot;&gt;\n&lt;div class=&quot;availability&quot;&gt;Disponível para retirada imediata&lt;/div&gt;\n&lt;h3&gt;Descrição&lt;/h3&gt;\n&lt;p&gt;Sapateira&lt;br/&gt;100 x 41 x 56 cm&lt;/p&gt;\n&lt;/div&gt;",
    "id": "b0ac7cd2-751a-4e46-9373-64589d310515",
    "images": [
      "assets/img/sapateira/20250503_155657.jpg",
      "assets/img/sapateira/20250503_155705.jpg",
      "assets/img/sapateira/20250503_155639.jpg"
    ]
  },
  {
    "title": "Sofá 3 lugares",
    "item_url": "item-sofa-pt.html",
    "image_url": "assets/img/sofa/eskilstuna-3-seat-sofa-with-chaise-longue-hillared-beige__1256275_pe924995_s5.avif",
    "price_old": "€ 399.00",
    "price": "🔥€ 360.00",
    "status": "disponível agora",
    "description": "&lt;div class=&quot;item-description&quot;&gt;\n&lt;div class=&quot;availability&quot;&gt;Disponível para retirada imediata&lt;/div&gt;\n&lt;h3&gt;Descrição&lt;/h3&gt;\n&lt;p&gt;ESKILSTUNA&lt;br/&gt;3-seat sofa with chaise longue, Hillared beige&lt;br/&gt;Here´s a sofa that allows you to\n                    really relax and feel comfortable. ESKILSTUNA sofa has an extra-high back, adjustable headrests and\n                    chaise longues that you can easily push out with your feet.&lt;br/&gt;Product details&lt;br/&gt;You can really\n                    loosen up and relax in comfort because the high back on this sofa provides extra support for your\n                    neck.&lt;br/&gt;You can place the chaise longue section to the left or right of the sofa, and switch\n                    whenever you like.&lt;br/&gt;If you want a comfortable chaise lounge, just push out the seating section\n                    with your feet.&lt;br/&gt;10 year guarantee. Read about the terms in the guarantee\n                    brochure.&lt;br/&gt;Measurements&lt;br/&gt;Depth: 162 cm&lt;br/&gt;Height: 100 cm&lt;br/&gt;Width: 268 cm&lt;br/&gt;Depth chaise\n                    longue: 162 cm&lt;br/&gt;Seat height: 45 cm&lt;br/&gt;Seat depth: 56 cm&lt;br/&gt;Seat width: 225 cm&lt;br/&gt;Seat depth,\n                    chaise longue: 104 cm&lt;br/&gt;Armrest height: 61 cm&lt;br/&gt;Free height under furniture: 5 cm&lt;/p&gt;\n&lt;/div&gt;",
    "id": "4004072e-fedb-4547-906a-cab4e1b6f776",
    "images": [
      "assets/img/sofa/eskilstuna-3-seat-sofa-with-chaise-longue-hillared-beige__1256275_pe924995_s5.avif",
      "assets/img/sofa/eskilstuna-3-seat-sofa-with-chaise-longue-hillared-beige__1256288_pe925008_s5.avif",
      "assets/img/sofa/eskilstuna-3-seat-sofa-with-chaise-longue-hillared-beige__1256276_pe924993_s5.avif"
    ]
  },
  {
    "title": "Tabua de passar roupa",
    "item_url": "item-ta_bua_de_engomar_sevilha-pt.html",
    "image_url": "assets/img/tabua_de_engomar_sevilha/400420_tabua_de_engomar_sevilha_homa_1.webp",
    "price_old": "€ 20.00",
    "price": "€ 15.00",
    "status": "disponível agora",
    "description": "&lt;div class=&quot;item-description&quot;&gt;\n&lt;div class=&quot;availability&quot;&gt;Disponível para retirada imediata&lt;/div&gt;\n&lt;h3&gt;Descrição&lt;/h3&gt;\n&lt;p&gt;Tábua de engomar sevilha&lt;br/&gt;Tábua De Engomar Sevilha | 90x32x110cm&lt;br/&gt;Material: metal&lt;br/&gt;Cor:\n                    multicolor&lt;br/&gt;Peso do Produto: 5,10&lt;br/&gt;Altura: 90,0 cm&lt;br/&gt;Comprimento: 110,0 cm&lt;br/&gt;Largura: 32,0 cm\n                &lt;/p&gt;\n&lt;/div&gt;",
    "id": "3f758101-522d-4eb2-b7dc-dd07a588ee44",
    "images": [
      "assets/img/tabua_de_engomar_sevilha/400420_tabua_de_engomar_sevilha_homa_1.webp"
    ]
  },
  {
    "title": "TV LG 65NANO766QA",
    "item_url": "item-tv_lg_65-pt.html",
    "image_url": "assets/img/tv_lg_65/d5f5a1bbd2c12f412c85669ece84fa1bf370ff04.jpeg",
    "price_old": "€ 680.00",
    "price": "🔥€ 410.00",
    "status": "disponível agora",
    "description": "&lt;div class=&quot;item-description&quot;&gt;\n&lt;div class=&quot;availability&quot;&gt;Disponível para retirada imediata&lt;/div&gt;\n&lt;h3&gt;Descrição&lt;/h3&gt;\n&lt;p&gt;TV LG 65NANO766QA&lt;br/&gt;Sobre o produto&lt;br/&gt;TV LG 65NANO766QA (Nano Cell - 65&#x27;&#x27; - 165 cm - 4K Ultra HD -\n                    Smart TV)&lt;br/&gt;Descubra a verdadeira essência das cores puras.&lt;br/&gt;Embarque numa nova experiência de\n                    cor graças à pureza das TVs NanoCell da LG, com resolução 4K Real.&lt;br/&gt;&lt;br/&gt;Uma abordagem essencial da\n                    cor&lt;br/&gt;A tecnologia NanoCell da LG usa nanopartículas para filtrar as cores impuras dos comprimentos\n                    de onda RGB.&lt;br/&gt;&lt;br/&gt;Cores puras e otimizadas pelo poder do processador&lt;br/&gt;O processador α5 Gen5 AI\n                    4K analisa os conteúdos na sua forma original e otimiza-os para a máxima qualidade.&lt;br/&gt;&lt;br/&gt;A melhor\n                    experiência de Gaming começa aqui&lt;br/&gt;Usufrua de uma jogabilidade rápida e suave e mergulhe\n                    diretamente na ação do seu jogo.&lt;br/&gt;&lt;br/&gt;Para quê complicar?&lt;br/&gt;A compatibilidade com a plataforma\n                    Google Stadia dá-lhe um acesso instantâneo a milhares de jogos, sem precisar de hardware\n                    adicional.&lt;br/&gt;&lt;br/&gt;Junte-se ao seu herói favorito&lt;br/&gt;As TVs NanoCell da LG são agora compatíveis com\n                    NVIDIA GEFORCE Now, uma plataforma de Cloud Gaming que lhe oferece os mais recentes jogos de PC,\n                    diretamente na sua TV. Graças à sua compatibilidade com vários dispositivos, pode ainda retomar na\n                    sua TV o jogo que começou noutra plataforma ligada à GEFORCE Now.&lt;/p&gt;\n&lt;/div&gt;",
    "id": "0f846003-c9a0-4dbc-876f-b3c3bfb18b02",
    "images": [
      "assets/img/tv_lg_65/d5f5a1bbd2c12f412c85669ece84fa1bf370ff04.jpeg",
      "assets/img/tv_lg_65/20250503_155234.jpg",
      "assets/img/tv_lg_65/20250503_155250.jpg",
      "assets/img/tv_lg_65/2e26def52601e00a670d934b47c534d5e727ebf4.webp",
      "assets/img/tv_lg_65/20250503_155241.jpg",
      "assets/img/tv_lg_65/20250503_155242.jpg",
      "assets/img/tv_lg_65/399a8c6752edb2d8d4f58144ea682f68a51ff8be.jpeg"
    ]
  },
  {
    "title": "Dreo 25dB Ventilador de torre\ninteligente (Alexa / Google)",
    "item_url": "item-ventilador_de_torre_inteligente_dreo_25_db-pt.html",
    "image_url": "assets/img/ventilador_de_torre_inteligente_dreo_25_db/81azhrozsll_ac_sl1500_.jpg",
    "price_old": "€ 90.00",
    "price": "🔥€ 49.00",
    "status": "disponível agora",
    "description": "&lt;div class=&quot;item-description&quot;&gt;\n&lt;div class=&quot;availability&quot;&gt;Disponível para retirada imediata&lt;/div&gt;\n&lt;h3&gt;Descrição&lt;/h3&gt;\n&lt;p&gt;contre um vento para todas as situações: Com 9 velocidades e 4 modos diferentes, este ventilador de\n                    chão vem equipado com tudo o que precisa para refrescar o seu verão, além disso, pode aceder\n                    facilmente a todas essas funções através do painel de controlo e do ecrã incorporado.&lt;br/&gt;O vento\n                    adapta-se ao seu quarto: Usando um algoritmo inteligente e sensores de temperatura precisos, este\n                    ventilador de torre altera automaticamente as velocidades do vento para manter o seu quarto\n                    confortavelmente fresco, mesmo com mudanças de temperatura ao longo do dia.&lt;br/&gt;Mergulhe no modo de\n                    sono: Este ventilador de torre com controlo remoto é o companheiro ideal para dormir. Quando se está\n                    a preparar para dormir, com o toque de um botão, este modo de sono do ventilador de torre ajustará\n                    automaticamente a velocidade do vento ao ruído e atenuará as luzes do ecrã.&lt;br/&gt;Detalhes técnicos&lt;/p&gt;\n&lt;/div&gt;",
    "id": "dbd6ff6e-8d20-43c1-a779-b28e2c8a3b4c",
    "images": [
      "assets/img/ventilador_de_torre_inteligente_dreo_25_db/81azhrozsll_ac_sl1500_.jpg",
      "assets/img/ventilador_de_torre_inteligente_dreo_25_db/8166yptclyl_ac_sl1500_.jpg",
      "assets/img/ventilador_de_torre_inteligente_dreo_25_db/20250503_155534.jpg",
      "assets/img/ventilador_de_torre_inteligente_dreo_25_db/20250503_155521.jpg",
      "assets/img/ventilador_de_torre_inteligente_dreo_25_db/20250503_155527.jpg",
      "assets/img/ventilador_de_torre_inteligente_dreo_25_db/20250503_155530.jpg",
      "assets/img/ventilador_de_torre_inteligente_dreo_25_db/718pjyv8tzl_ac_sl1500_.jpg",
      "assets/img/ventilador_de_torre_inteligente_dreo_25_db/81vmpokg3l_ac_sl1500_.jpg",
      "assets/img/ventilador_de_torre_inteligente_dreo_25_db/81hp7fcyl_ac_sl1500_.jpg",
      "assets/img/ventilador_de_torre_inteligente_dreo_25_db/71bszbzh2rl_ac_sl1500_.jpg",
      "assets/img/ventilador_de_torre_inteligente_dreo_25_db/711b0d596tl_ac_sl1500_.jpg"
    ]
  }
]
